hatch_dotenv/__about__.py
hatch_dotenv/__init__.py
hatch_dotenv/hooks.py
hatch_dotenv/plugin.py
hatch_dotenv-0.1.2.dist-info/METADATA
hatch_dotenv-0.1.2.dist-info/WHEEL
hatch_dotenv-0.1.2.dist-info/entry_points.txt
hatch_dotenv-0.1.2.dist-info/licenses/LICENSE
hatch_dotenv-0.1.2.dist-info/RECORD
