Metadata-Version: 2.4
Name: hatch-dotenv
Version: 0.1.2
Summary: Hatch plugin that enables dotenv support
Project-URL: Documentation, https://github.com/Dniskk/hatch-dotenv#readme
Project-URL: Issues, https://github.com/Dniskk/hatch-dotenv/issues
Project-URL: Source, https://github.com/Dniskk/hatch-dotenv
Author-email: Dennis Cost <dnis.kk@gmail.com>
License-Expression: MIT
License-File: LICENSE
Classifier: Framework :: Hatch
Classifier: Programming Language :: Python
Classifier: Programming Language :: Python :: 3.10
Classifier: Programming Language :: Python :: 3.11
Classifier: Programming Language :: Python :: 3.12
Classifier: Programming Language :: Python :: 3.13
Classifier: Programming Language :: Python :: 3.14
Classifier: Programming Language :: Python :: Implementation :: CPython
Classifier: Programming Language :: Python :: Implementation :: PyPy
Requires-Python: <=3.14,>=3.10
Requires-Dist: hatch
Requires-Dist: python-dotenv>=1.0.0
Requires-Dist: typing-extensions>=4.0.0
